[
	{
		"__TYPE__": "SharedSliceContent",
		"variation": "default",
		"primary": {
			"title": {
				"__TYPE__": "StructuredTextContent",
				"value": [
					{
						"type": "heading2",
						"content": {
							"text": "Worry"
						}
					}
				]
			},
			"body": {
				"__TYPE__": "StructuredTextContent",
				"value": [
					{
						"type": "paragraph",
						"content": {
							"text": "In aute do culpa nostrud id sint veniam tempor."
						}
					}
				]
			},
			"button_link": {
				"__TYPE__": "LinkContent",
				"value": {
					"__TYPE__": "ExternalLink",
					"url": "https://slicemachine.dev"
				}
			},
			"button_label": {
				"__TYPE__": "FieldContent",
				"value": "week",
				"type": "Text"
			}
		},
		"items": []
	}
]